ptychodus/__init__.py
ptychodus/__main__.py
ptychodus/cli.py
ptychodus/convert_to_ptychodus.py
ptychodus/ptychodus_bdp.py
ptychodus/ptychodus_stream_processor.py
ptychodus/api/__init__.py
ptychodus/api/diffraction.py
ptychodus/api/fluorescence.py
ptychodus/api/geometry.py
ptychodus/api/io.py
ptychodus/api/object.py
ptychodus/api/observer.py
ptychodus/api/parametric.py
ptychodus/api/plugins.py
ptychodus/api/probe.py
ptychodus/api/probe_positions.py
ptychodus/api/product.py
ptychodus/api/propagator.py
ptychodus/api/reconstructor.py
ptychodus/api/settings.py
ptychodus/api/tree.py
ptychodus/api/typing.py
ptychodus/api/units.py
ptychodus/api/visualization.py
ptychodus/api/workflow.py
ptychodus/controller/__init__.py
ptychodus/controller/automation.py
ptychodus/controller/core.py
ptychodus/controller/data.py
ptychodus/controller/helpers.py
ptychodus/controller/image.py
ptychodus/controller/memory.py
ptychodus/controller/parametric.py
ptychodus/controller/ptychonn.py
ptychodus/controller/ptychopinn.py
ptychodus/controller/reconstructor.py
ptychodus/controller/settings.py
ptychodus/controller/agent/__init__.py
ptychodus/controller/agent/core.py
ptychodus/controller/agent/item_delegate.py
ptychodus/controller/agent/list_model.py
ptychodus/controller/diffraction/__init__.py
ptychodus/controller/diffraction/core.py
ptychodus/controller/diffraction/dataset.py
ptychodus/controller/diffraction/dataset_layout.py
ptychodus/controller/diffraction/wizard/__init__.py
ptychodus/controller/diffraction/wizard/core.py
ptychodus/controller/diffraction/wizard/files.py
ptychodus/controller/diffraction/wizard/metadata.py
ptychodus/controller/diffraction/wizard/patterns.py
ptychodus/controller/globus/__init__.py
ptychodus/controller/globus/authorization.py
ptychodus/controller/globus/compute.py
ptychodus/controller/globus/controller.py
ptychodus/controller/globus/execution.py
ptychodus/controller/globus/input_data.py
ptychodus/controller/globus/output_data.py
ptychodus-1.2.dist-info/licenses/LICENSE
ptychodus-1.2.dist-info/METADATA
ptychodus-1.2.dist-info/WHEEL
ptychodus-1.2.dist-info/entry_points.txt
ptychodus-1.2.dist-info/top_level.txt
ptychodus-1.2.dist-info/RECORD
