Metadata-Version: 2.4
Name: ptychodus
Version: 1.2
Summary: Ptychodus is a ptychography data pipeline application.
License-Expression: BSD-3-Clause
Requires-Python: >=3.10
License-File: LICENSE
Requires-Dist: h5py>=3
Requires-Dist: hdf5plugin
Requires-Dist: matplotlib
Requires-Dist: numpy
Requires-Dist: psutil
Requires-Dist: pyyaml
Requires-Dist: requests
Requires-Dist: scikit-image
Requires-Dist: scipy
Requires-Dist: tifffile
Requires-Dist: watchdog
Provides-Extra: globus
Requires-Dist: gladier; extra == "globus"
Requires-Dist: gladier-tools>=0.5.4; extra == "globus"
Provides-Extra: gui
Requires-Dist: PyQt5; extra == "gui"
Provides-Extra: ptychonn
Requires-Dist: ptychonn==0.3.*,>=0.3.7; extra == "ptychonn"
Provides-Extra: ptychi
Requires-Dist: ptychi==1.*,>=1.2.0; extra == "ptychi"
Dynamic: license-file
